vvicorn/__init__.py
vvicorn/server.py
vvicorn-0.1.3.dist-info/LICENSE
vvicorn-0.1.3.dist-info/WHEEL
vvicorn-0.1.3.dist-info/METADATA
vvicorn-0.1.3.dist-info/RECORD
