Metadata-Version: 2.1
Name: vvicorn
Version: 0.1.3
Summary: Uvicorn's logging wrapped with ulogcorn
Author: Joy
Author-email: icocoabeans@gmail.com
Requires-Python: >=3.7,<4.0
Classifier: Programming Language :: Python :: 3
Classifier: Programming Language :: Python :: 3.10
Classifier: Programming Language :: Python :: 3.7
Classifier: Programming Language :: Python :: 3.8
Classifier: Programming Language :: Python :: 3.9
Requires-Dist: ulogcorn (>=0.4.2,<0.5.0)
